[
  {
    "nombre": "Café",
    "categoriaID": "9",
    "precio": "400"
  },
  {
    "nombre": "Café con leche",
    "categoriaID": "9",
    "precio": "500"
  },
  {
    "nombre": "Lágrima",
    "categoriaID": "9",
    "precio": "5200"
  },
  {
    "nombre": "Licuado de banana",
    "categoriaID": "9",
    "precio": "900"
  },
  {
    "nombre": "Licuado de durazno",
    "categoriaID": "9",
    "precio": "1100"
  },
  {
    "nombre": "Licuado de frutilla",
    "categoriaID": "9",
    "precio": "1200"
  },
  {
    "nombre": "Té",
    "categoriaID": "9",
    "precio": "400"
  },
  {
    "nombre": "Té verde",
    "categoriaID": "9",
    "precio": "500"
  },
  {
    "nombre": "Fanta 500ml",
    "categoriaID": "8",
    "precio": "500"
  },
  {
    "nombre": "Coca Cola 500ml",
    "categoriaID": "8",
    "precio": "500"
  },
  {
    "nombre": "Agua sin gas 500ml",
    "categoriaID": "8",
    "precio": "500"
  },
  {
    "nombre": "Aquarius de Manzana 500ml",
    "categoriaID": "8",
    "precio": "500"
  },
  {
    "nombre": "Aquarius de Naranja 500ml",
    "categoriaID": "8",
    "precio": "500"
  },
  {
    "nombre": "Aquarius de Pomelo 500ml",
    "categoriaID": "8",
    "precio": "3200"
  }
]
